thumbnail/__init__.py
thumbnail/apps.py
thumbnail/backend.py
thumbnail/models.py
thumbnail/tasks.py
thumbnail/utils.py
thumbnail/conf/__init__.py
thumbnail/conf/settings.py
thumbnail/templatetags/__init__.py
thumbnail/templatetags/thumbnail_tags.py
pod_ast-0.1.1.dist-info/LICENSE
pod_ast-0.1.1.dist-info/METADATA
pod_ast-0.1.1.dist-info/WHEEL
pod_ast-0.1.1.dist-info/top_level.txt
pod_ast-0.1.1.dist-info/RECORD
